LICENSE
MANIFEST.in
README.rst
setup.py
alchemysession/__init__.py
alchemysession/core.py
alchemysession/core_mysql.py
alchemysession/core_postgres.py
alchemysession/core_sqlite.py
alchemysession/orm.py
alchemysession/sqlalchemy.py
telethon_session_sqlalchemy_fork.egg-info/PKG-INFO
telethon_session_sqlalchemy_fork.egg-info/SOURCES.txt
telethon_session_sqlalchemy_fork.egg-info/dependency_links.txt
telethon_session_sqlalchemy_fork.egg-info/requires.txt
telethon_session_sqlalchemy_fork.egg-info/top_level.txt