Metadata-Version: 1.2
Name: telethon-session-sqlalchemy-fork
Version: 0.2.16
Summary: SQLAlchemy backend for Telethon session storage
Home-page: https://github.com/tulir/telethon-session-sqlalchemy
Author: Vitor Daniel
Author-email: vitor036daniel@gmail.com
License: UNKNOWN
Platform: UNKNOWN
Classifier: Development Status :: 4 - Beta
Classifier: License :: OSI Approved :: MIT License
Classifier: Programming Language :: Python
Classifier: Programming Language :: Python :: 3
Classifier: Programming Language :: Python :: 3.6
Classifier: Programming Language :: Python :: 3.7
Classifier: Programming Language :: Python :: 3.8
Classifier: Programming Language :: Python :: 3.9
Requires-Python: ~=3.5
